{"schema_version":"2.0","install_options":{"debug":false,"strict":false,"force":false},"metrics":{"start_time":1767945961171,"completion_time":1767945962569},"links":{"bin":{"stylua":"stylua"},"opt":{},"share":{}},"source":{"raw":{"id":"pkg:github/johnnymorganz/stylua@v2.3.1","asset":[{"file":"stylua-macos-aarch64.zip","target":"darwin_arm64","bin":"stylua"},{"file":"stylua-macos-x86_64.zip","target":"darwin_x64","bin":"stylua"},{"file":"stylua-linux-x86_64.zip","target":"linux_x64_gnu","bin":"stylua"},{"file":"stylua-linux-aarch64.zip","target":"linux_arm64_gnu","bin":"stylua"},{"file":"stylua-linux-x86_64-musl.zip","target":"linux_x64","bin":"stylua"},{"file":"stylua-windows-x86_64.zip","target":"win_x64","bin":"stylua.exe"}]},"type":"registry+v1","id":"pkg:github/johnnymorganz/stylua@v2.3.1"},"registry":{"name":"mason-registry","version":"2026-01-09-snug-dimple","proto":"github","namespace":"mason-org","checksums":{"registry.json":"eb1e9fc70973e48830669dee3e3e4cbccb41c3e437cc9d019f3906807a9e3f6e","registry.json.zip":"81d745228b3204766e45883bdb73290f14289cbf8563d7b8e79b8f02036d99ff"}},"name":"stylua"}